{"project_id":1,"task_count":308726,"sum_completedcount_corr":2381065,"avg_completedcount_corr":7.717,"sum_yes":374299,"sum_maybe":122255,"sum_badimage":45333,"avg_agree":0.718,"sum_a_class01":158215,"sum_a_class02":32409,"sum_a_class03":48956,"sum_a_class04":57214,"sum_a_class05":11932,"case_no_bad":11077,"case_yes_no":72396,"case_no_maybe":28219,"case_yes_maybe":5358,"case_yes_bad":458,"case_maybe_bad":224}
{"project_id":4,"task_count":387156,"sum_completedcount_corr":2936545,"avg_completedcount_corr":7.588,"sum_yes":262988,"sum_maybe":82412,"sum_badimage":121921,"avg_agree":0.833,"sum_a_class01":271247,"sum_a_class02":23015,"sum_a_class03":54231,"sum_a_class04":30217,"sum_a_class05":8446,"case_no_bad":27580,"case_yes_no":46635,"case_no_maybe":21561,"case_yes_maybe":2231,"case_yes_bad":773,"case_maybe_bad":1217}
{"project_id":5,"task_count":253518,"sum_completedcount_corr":1522167,"avg_completedcount_corr":6.006,"sum_yes":137374,"sum_maybe":39151,"sum_badimage":46283,"avg_agree":0.861,"sum_a_class01":195191,"sum_a_class02":6203,"sum_a_class03":20247,"sum_a_class04":27050,"sum_a_class05":4827,"case_no_bad":11661,"case_yes_no":25233,"case_no_maybe":11319,"case_yes_maybe":1644,"case_yes_bad":246,"case_maybe_bad":387}
{"project_id":8,"task_count":360532,"sum_completedcount_corr":1609468,"avg_completedcount_corr":4.470,"sum_yes":400686,"sum_maybe":67461,"sum_badimage":26249,"avg_agree":0.738,"sum_a_class01":208061,"sum_a_class02":18059,"sum_a_class03":37703,"sum_a_class04":82704,"sum_a_class05":14005,"case_no_bad":8632,"case_yes_no":93438,"case_no_maybe":22878,"case_yes_maybe":6379,"case_yes_bad":665,"case_maybe_bad":158}
{"project_id":14,"task_count":199475,"sum_completedcount_corr":1908284,"avg_completedcount_corr":9.570,"sum_yes":45958,"sum_maybe":34095,"sum_badimage":112240,"avg_agree":0.885,"sum_a_class01":155843,"sum_a_class02":13958,"sum_a_class03":16905,"sum_a_class04":11117,"sum_a_class05":1652,"case_no_bad":17241,"case_yes_no":9937,"case_no_maybe":9720,"case_yes_maybe":713,"case_yes_bad":361,"case_maybe_bad":955}
{"project_id":124,"task_count":282510,"sum_completedcount_corr":1384793,"avg_completedcount_corr":4.903,"sum_yes":46680,"sum_maybe":21945,"sum_badimage":114580,"avg_agree":0.900,"sum_a_class01":229800,"sum_a_class02":14426,"sum_a_class03":20959,"sum_a_class04":14869,"sum_a_class05":2456,"case_no_bad":25037,"case_yes_no":9638,"case_no_maybe":9404,"case_yes_maybe":850,"case_yes_bad":601,"case_maybe_bad":1136}
{"project_id":303,"task_count":266179,"sum_completedcount_corr":1093469,"avg_completedcount_corr":4.109,"sum_yes":40389,"sum_maybe":18457,"sum_badimage":81178,"avg_agree":0.891,"sum_a_class01":215647,"sum_a_class02":8878,"sum_a_class03":16856,"sum_a_class04":22066,"sum_a_class05":2732,"case_no_bad":21628,"case_yes_no":11726,"case_no_maybe":10511,"case_yes_maybe":523,"case_yes_bad":521,"case_maybe_bad":891}
{"project_id":407,"task_count":134576,"sum_completedcount_corr":553252,"avg_completedcount_corr":4.112,"sum_yes":22857,"sum_maybe":11185,"sum_badimage":18279,"avg_agree":0.889,"sum_a_class01":108110,"sum_a_class02":5549,"sum_a_class03":8784,"sum_a_class04":10543,"sum_a_class05":1590,"case_no_bad":8589,"case_yes_no":7906,"case_no_maybe":6954,"case_yes_maybe":287,"case_yes_bad":131,"case_maybe_bad":155}
{"project_id":565,"task_count":351022,"sum_completedcount_corr":2061964,"avg_completedcount_corr":5.877,"sum_yes":149517,"sum_maybe":44992,"sum_badimage":124127,"avg_agree":0.890,"sum_a_class01":274895,"sum_a_class02":29147,"sum_a_class03":28920,"sum_a_class04":14842,"sum_a_class05":3218,"case_no_bad":25172,"case_yes_no":20841,"case_no_maybe":14193,"case_yes_maybe":3252,"case_yes_bad":764,"case_maybe_bad":2267}
{"project_id":692,"task_count":222070,"sum_completedcount_corr":989897,"avg_completedcount_corr":4.460,"sum_yes":90833,"sum_maybe":14470,"sum_badimage":64705,"avg_agree":0.894,"sum_a_class01":180275,"sum_a_class02":10094,"sum_a_class03":13492,"sum_a_class04":15929,"sum_a_class05":2280,"case_no_bad":16143,"case_yes_no":13501,"case_no_maybe":5542,"case_yes_maybe":1007,"case_yes_bad":622,"case_maybe_bad":1048}
{"project_id":798,"task_count":1957,"sum_completedcount_corr":8038,"avg_completedcount_corr":4.109,"sum_yes":2652,"sum_maybe":349,"sum_badimage":975,"avg_agree":0.730,"sum_a_class01":1061,"sum_a_class02":38,"sum_a_class03":505,"sum_a_class04":222,"sum_a_class05":131,"case_no_bad":165,"case_yes_no":410,"case_no_maybe":90,"case_yes_maybe":51,"case_yes_bad":5,"case_maybe_bad":19}
{"project_id":922,"task_count":330592,"sum_completedcount_corr":1321347,"avg_completedcount_corr":4.004,"sum_yes":278572,"sum_maybe":24056,"sum_badimage":172519,"avg_agree":0.796,"sum_a_class01":216498,"sum_a_class02":16615,"sum_a_class03":37526,"sum_a_class04":54662,"sum_a_class05":5291,"case_no_bad":56055,"case_yes_no":33785,"case_no_maybe":11172,"case_yes_maybe":1522,"case_yes_bad":1141,"case_maybe_bad":1702}
{"project_id":1166,"task_count":202016,"sum_completedcount_corr":815976,"avg_completedcount_corr":4.040,"sum_yes":30650,"sum_maybe":13222,"sum_badimage":36179,"avg_agree":0.907,"sum_a_class01":169094,"sum_a_class02":6397,"sum_a_class03":12018,"sum_a_class04":12635,"sum_a_class05":1872,"case_no_bad":10388,"case_yes_no":10487,"case_no_maybe":8043,"case_yes_maybe":395,"case_yes_bad":242,"case_maybe_bad":570}
{"project_id":1333,"task_count":147533,"sum_completedcount_corr":742331,"avg_completedcount_corr":5.033,"sum_yes":29816,"sum_maybe":13077,"sum_badimage":45001,"avg_agree":0.892,"sum_a_class01":114970,"sum_a_class02":14314,"sum_a_class03":13375,"sum_a_class04":3815,"sum_a_class05":1059,"case_no_bad":11621,"case_yes_no":9134,"case_no_maybe":6878,"case_yes_maybe":189,"case_yes_bad":286,"case_maybe_bad":428}
{"project_id":1440,"task_count":284373,"sum_completedcount_corr":1065266,"avg_completedcount_corr":3.747,"sum_yes":42955,"sum_maybe":21424,"sum_badimage":71555,"avg_agree":0.890,"sum_a_class01":232032,"sum_a_class02":8092,"sum_a_class03":14561,"sum_a_class04":25851,"sum_a_class05":3837,"case_no_bad":18029,"case_yes_no":13820,"case_no_maybe":12052,"case_yes_maybe":899,"case_yes_bad":634,"case_maybe_bad":1272}
{"project_id":1599,"task_count":189761,"sum_completedcount_corr":781449,"avg_completedcount_corr":4.118,"sum_yes":5426,"sum_maybe":8478,"sum_badimage":4223,"avg_agree":0.960,"sum_a_class01":175739,"sum_a_class02":2911,"sum_a_class03":5950,"sum_a_class04":4442,"sum_a_class05":719,"case_no_bad":3621,"case_yes_no":2739,"case_no_maybe":6821,"case_yes_maybe":97,"case_yes_bad":0,"case_maybe_bad":0}
{"project_id":1788,"task_count":134412,"sum_completedcount_corr":537418,"avg_completedcount_corr":3.998,"sum_yes":8996,"sum_maybe":5367,"sum_badimage":6021,"avg_agree":0.951,"sum_a_class01":122628,"sum_a_class02":2521,"sum_a_class03":4047,"sum_a_class04":4757,"sum_a_class05":459,"case_no_bad":3819,"case_yes_no":3201,"case_no_maybe":3875,"case_yes_maybe":119,"case_yes_bad":12,"case_maybe_bad":54}
{"project_id":1901,"task_count":343872,"sum_completedcount_corr":1470717,"avg_completedcount_corr":4.277,"sum_yes":16357,"sum_maybe":10637,"sum_badimage":12307,"avg_agree":0.959,"sum_a_class01":315941,"sum_a_class02":8315,"sum_a_class03":14629,"sum_a_class04":4167,"sum_a_class05":820,"case_no_bad":10103,"case_yes_no":8210,"case_no_maybe":8083,"case_yes_maybe":216,"case_yes_bad":16,"case_maybe_bad":26}
{"project_id":2020,"task_count":38047,"sum_completedcount_corr":162556,"avg_completedcount_corr":4.273,"sum_yes":20011,"sum_maybe":3210,"sum_badimage":435,"avg_agree":0.879,"sum_a_class01":29211,"sum_a_class02":1929,"sum_a_class03":5219,"sum_a_class04":1265,"sum_a_class05":423,"case_no_bad":368,"case_yes_no":5483,"case_no_maybe":2278,"case_yes_maybe":87,"case_yes_bad":8,"case_maybe_bad":0}
{"project_id":2158,"task_count":307789,"sum_completedcount_corr":1335225,"avg_completedcount_corr":4.339,"sum_yes":75366,"sum_maybe":24322,"sum_badimage":28581,"avg_agree":0.910,"sum_a_class01":255603,"sum_a_class02":13260,"sum_a_class03":24697,"sum_a_class04":11588,"sum_a_class05":2641,"case_no_bad":10014,"case_yes_no":19485,"case_no_maybe":16241,"case_yes_maybe":1087,"case_yes_bad":214,"case_maybe_bad":308}
{"project_id":2293,"task_count":85681,"sum_completedcount_corr":353522,"avg_completedcount_corr":4.128,"sum_yes":19537,"sum_maybe":4847,"sum_badimage":6200,"avg_agree":0.929,"sum_a_class01":74125,"sum_a_class02":3230,"sum_a_class03":5427,"sum_a_class04":2431,"sum_a_class05":468,"case_no_bad":2086,"case_yes_no":4891,"case_no_maybe":3589,"case_yes_maybe":91,"case_yes_bad":36,"case_maybe_bad":40}
{"project_id":2473,"task_count":280354,"sum_completedcount_corr":990917,"avg_completedcount_corr":3.535,"sum_yes":33093,"sum_maybe":10206,"sum_badimage":23715,"avg_agree":0.920,"sum_a_class01":243534,"sum_a_class02":3950,"sum_a_class03":8604,"sum_a_class04":22621,"sum_a_class05":1645,"case_no_bad":18593,"case_yes_no":8480,"case_no_maybe":7157,"case_yes_maybe":445,"case_yes_bad":87,"case_maybe_bad":39}
{"project_id":2644,"task_count":260982,"sum_completedcount_corr":1067652,"avg_completedcount_corr":4.095,"sum_yes":121346,"sum_maybe":22069,"sum_badimage":37187,"avg_agree":0.868,"sum_a_class01":200711,"sum_a_class02":13102,"sum_a_class03":17962,"sum_a_class04":25650,"sum_a_class05":3557,"case_no_bad":15299,"case_yes_no":23510,"case_no_maybe":11818,"case_yes_maybe":1506,"case_yes_bad":667,"case_maybe_bad":482}
{"project_id":2671,"task_count":34152,"sum_completedcount_corr":247409,"avg_completedcount_corr":7.247,"sum_yes":49991,"sum_maybe":2290,"sum_badimage":2413,"avg_agree":0.880,"sum_a_class01":23545,"sum_a_class02":6379,"sum_a_class03":3918,"sum_a_class04":308,"sum_a_class05":2,"case_no_bad":1194,"case_yes_no":7637,"case_no_maybe":1422,"case_yes_maybe":23,"case_yes_bad":2,"case_maybe_bad":0}
{"project_id":2809,"task_count":372694,"sum_completedcount_corr":1352435,"avg_completedcount_corr":3.632,"sum_yes":11217,"sum_maybe":16727,"sum_badimage":89203,"avg_agree":0.930,"sum_a_class01":329342,"sum_a_class02":5978,"sum_a_class03":10305,"sum_a_class04":24810,"sum_a_class05":2259,"case_no_bad":20535,"case_yes_no":5817,"case_no_maybe":10565,"case_yes_maybe":100,"case_yes_bad":893,"case_maybe_bad":2128}
{"project_id":2978,"task_count":261640,"sum_completedcount_corr":1182873,"avg_completedcount_corr":4.527,"sum_yes":208805,"sum_maybe":41712,"sum_badimage":24655,"avg_agree":0.819,"sum_a_class01":176219,"sum_a_class02":19574,"sum_a_class03":34346,"sum_a_class04":24698,"sum_a_class05":6803,"case_no_bad":13234,"case_yes_no":34360,"case_no_maybe":20716,"case_yes_maybe":3938,"case_yes_bad":830,"case_maybe_bad":280}
{"project_id":3121,"task_count":250096,"sum_completedcount_corr":960982,"avg_completedcount_corr":3.843,"sum_yes":27316,"sum_maybe":16394,"sum_badimage":15390,"avg_agree":0.932,"sum_a_class01":219684,"sum_a_class02":5857,"sum_a_class03":11004,"sum_a_class04":12266,"sum_a_class05":1285,"case_no_bad":7852,"case_yes_no":7341,"case_no_maybe":12455,"case_yes_maybe":436,"case_yes_bad":108,"case_maybe_bad":102}
{"project_id":3310,"task_count":278296,"sum_completedcount_corr":1106819,"avg_completedcount_corr":3.978,"sum_yes":36246,"sum_maybe":12324,"sum_badimage":9433,"avg_agree":0.943,"sum_a_class01":249023,"sum_a_class02":6970,"sum_a_class03":11231,"sum_a_class04":9954,"sum_a_class05":1118,"case_no_bad":6554,"case_yes_no":11234,"case_no_maybe":9193,"case_yes_maybe":432,"case_yes_bad":44,"case_maybe_bad":14}
{"project_id":3440,"task_count":349616,"sum_completedcount_corr":1475536,"avg_completedcount_corr":4.221,"sum_yes":9525,"sum_maybe":15013,"sum_badimage":58891,"avg_agree":0.937,"sum_a_class01":307141,"sum_a_class02":14475,"sum_a_class03":14644,"sum_a_class04":12208,"sum_a_class05":1148,"case_no_bad":23684,"case_yes_no":4483,"case_no_maybe":10745,"case_yes_maybe":114,"case_yes_bad":329,"case_maybe_bad":970}
{"project_id":3610,"task_count":231899,"sum_completedcount_corr":1540999,"avg_completedcount_corr":6.646,"sum_yes":21816,"sum_maybe":13710,"sum_badimage":68669,"avg_agree":0.926,"sum_a_class01":188722,"sum_a_class02":28753,"sum_a_class03":12506,"sum_a_class04":1880,"sum_a_class05":38,"case_no_bad":24556,"case_yes_no":6445,"case_no_maybe":9027,"case_yes_maybe":67,"case_yes_bad":101,"case_maybe_bad":296}
{"project_id":3764,"task_count":59085,"sum_completedcount_corr":360017,"avg_completedcount_corr":6.095,"sum_yes":14960,"sum_maybe":7038,"sum_badimage":2760,"avg_agree":0.934,"sum_a_class01":50325,"sum_a_class02":5465,"sum_a_class03":2588,"sum_a_class04":590,"sum_a_class05":117,"case_no_bad":1904,"case_yes_no":2303,"case_no_maybe":4681,"case_yes_maybe":169,"case_yes_bad":0,"case_maybe_bad":5}
{"project_id":3906,"task_count":192138,"sum_completedcount_corr":991809,"avg_completedcount_corr":5.165,"sum_yes":78874,"sum_maybe":11593,"sum_badimage":17028,"avg_agree":0.925,"sum_a_class01":162111,"sum_a_class02":13982,"sum_a_class03":12225,"sum_a_class04":2796,"sum_a_class05":1024,"case_no_bad":9930,"case_yes_no":9645,"case_no_maybe":6235,"case_yes_maybe":948,"case_yes_bad":111,"case_maybe_bad":109}
{"project_id":4103,"task_count":316233,"sum_completedcount_corr":1238885,"avg_completedcount_corr":3.918,"sum_yes":38660,"sum_maybe":22294,"sum_badimage":37420,"avg_agree":0.894,"sum_a_class01":258595,"sum_a_class02":10258,"sum_a_class03":17112,"sum_a_class04":26867,"sum_a_class05":3401,"case_no_bad":17749,"case_yes_no":18709,"case_no_maybe":15229,"case_yes_maybe":650,"case_yes_bad":236,"case_maybe_bad":310}
{"project_id":4242,"task_count":322318,"sum_completedcount_corr":1364828,"avg_completedcount_corr":4.235,"sum_yes":86711,"sum_maybe":23656,"sum_badimage":39440,"avg_agree":0.887,"sum_a_class01":255370,"sum_a_class02":16616,"sum_a_class03":26746,"sum_a_class04":19994,"sum_a_class05":3592,"case_no_bad":23340,"case_yes_no":21143,"case_no_maybe":15156,"case_yes_maybe":924,"case_yes_bad":159,"case_maybe_bad":371}
{"project_id":4355,"task_count":347454,"sum_completedcount_corr":1206812,"avg_completedcount_corr":3.473,"sum_yes":11568,"sum_maybe":9580,"sum_badimage":6830,"avg_agree":0.956,"sum_a_class01":322644,"sum_a_class02":2887,"sum_a_class03":4702,"sum_a_class04":16404,"sum_a_class05":817,"case_no_bad":6223,"case_yes_no":9568,"case_no_maybe":8257,"case_yes_maybe":79,"case_yes_bad":5,"case_maybe_bad":16}
{"project_id":4543,"task_count":51750,"sum_completedcount_corr":218403,"avg_completedcount_corr":4.221,"sum_yes":5777,"sum_maybe":4721,"sum_badimage":4868,"avg_agree":0.914,"sum_a_class01":43318,"sum_a_class02":1676,"sum_a_class03":4909,"sum_a_class04":1392,"sum_a_class05":455,"case_no_bad":2142,"case_yes_no":1949,"case_no_maybe":3525,"case_yes_maybe":31,"case_yes_bad":11,"case_maybe_bad":28}
{"project_id":4743,"task_count":243074,"sum_completedcount_corr":897754,"avg_completedcount_corr":3.695,"sum_yes":60659,"sum_maybe":17251,"sum_badimage":50356,"avg_agree":0.876,"sum_a_class01":193668,"sum_a_class02":6007,"sum_a_class03":12901,"sum_a_class04":27307,"sum_a_class05":3191,"case_no_bad":17886,"case_yes_no":15080,"case_no_maybe":9365,"case_yes_maybe":1246,"case_yes_bad":231,"case_maybe_bad":579}
{"project_id":4877,"task_count":238044,"sum_completedcount_corr":1899977,"avg_completedcount_corr":7.984,"sum_yes":113045,"sum_maybe":36468,"sum_badimage":47169,"avg_agree":0.897,"sum_a_class01":190753,"sum_a_class02":17036,"sum_a_class03":21531,"sum_a_class04":5779,"sum_a_class05":2945,"case_no_bad":11805,"case_yes_no":20008,"case_no_maybe":13848,"case_yes_maybe":701,"case_yes_bad":106,"case_maybe_bad":104}
{"project_id":5061,"task_count":126802,"sum_completedcount_corr":495181,"avg_completedcount_corr":3.906,"sum_yes":24432,"sum_maybe":7695,"sum_badimage":3756,"avg_agree":0.918,"sum_a_class01":108658,"sum_a_class02":3328,"sum_a_class03":6537,"sum_a_class04":7017,"sum_a_class05":1262,"case_no_bad":2932,"case_yes_no":8174,"case_no_maybe":5029,"case_yes_maybe":328,"case_yes_bad":5,"case_maybe_bad":7}
{"project_id":5169,"task_count":65334,"sum_completedcount_corr":307339,"avg_completedcount_corr":4.705,"sum_yes":11537,"sum_maybe":3329,"sum_badimage":18308,"avg_agree":0.899,"sum_a_class01":52127,"sum_a_class02":4194,"sum_a_class03":7230,"sum_a_class04":1188,"sum_a_class05":595,"case_no_bad":7858,"case_yes_no":2231,"case_no_maybe":1913,"case_yes_maybe":30,"case_yes_bad":83,"case_maybe_bad":161}
{"project_id":5291,"task_count":23503,"sum_completedcount_corr":125003,"avg_completedcount_corr":5.319,"sum_yes":3000,"sum_maybe":294,"sum_badimage":1059,"avg_agree":0.942,"sum_a_class01":20275,"sum_a_class02":2428,"sum_a_class03":689,"sum_a_class04":104,"sum_a_class05":7,"case_no_bad":571,"case_yes_no":2407,"case_no_maybe":170,"case_yes_maybe":4,"case_yes_bad":0,"case_maybe_bad":1}
{"project_id":5368,"task_count":57581,"sum_completedcount_corr":207852,"avg_completedcount_corr":3.610,"sum_yes":2802,"sum_maybe":1677,"sum_badimage":6419,"avg_agree":0.936,"sum_a_class01":51529,"sum_a_class02":599,"sum_a_class03":1613,"sum_a_class04":3562,"sum_a_class05":278,"case_no_bad":3558,"case_yes_no":886,"case_no_maybe":1135,"case_yes_maybe":15,"case_yes_bad":18,"case_maybe_bad":126}
{"project_id":5519,"task_count":28668,"sum_completedcount_corr":249704,"avg_completedcount_corr":8.710,"sum_yes":1426,"sum_maybe":1151,"sum_badimage":417,"avg_agree":0.982,"sum_a_class01":26933,"sum_a_class02":1495,"sum_a_class03":185,"sum_a_class04":55,"sum_a_class05":0,"case_no_bad":404,"case_yes_no":405,"case_no_maybe":885,"case_yes_maybe":4,"case_yes_bad":0,"case_maybe_bad":0}
{"project_id":5688,"task_count":13327,"sum_completedcount_corr":71689,"avg_completedcount_corr":5.379,"sum_yes":739,"sum_maybe":275,"sum_badimage":8,"avg_agree":0.985,"sum_a_class01":12870,"sum_a_class02":370,"sum_a_class03":61,"sum_a_class04":26,"sum_a_class05":0,"case_no_bad":7,"case_yes_no":208,"case_no_maybe":224,"case_yes_maybe":4,"case_yes_bad":0,"case_maybe_bad":0}
{"project_id":5870,"task_count":14222,"sum_completedcount_corr":52711,"avg_completedcount_corr":3.706,"sum_yes":685,"sum_maybe":191,"sum_badimage":174,"avg_agree":0.983,"sum_a_class01":13807,"sum_a_class02":48,"sum_a_class03":190,"sum_a_class04":160,"sum_a_class05":17,"case_no_bad":68,"case_yes_no":161,"case_no_maybe":155,"case_yes_maybe":0,"case_yes_bad":2,"case_maybe_bad":0}
{"project_id":5990,"task_count":10954,"sum_completedcount_corr":44085,"avg_completedcount_corr":4.025,"sum_yes":887,"sum_maybe":460,"sum_badimage":5910,"avg_agree":0.888,"sum_a_class01":8787,"sum_a_class02":149,"sum_a_class03":1296,"sum_a_class04":573,"sum_a_class05":149,"case_no_bad":1566,"case_yes_no":139,"case_no_maybe":178,"case_yes_maybe":16,"case_yes_bad":26,"case_maybe_bad":60}
{"project_id":6027,"task_count":1592,"sum_completedcount_corr":44417,"avg_completedcount_corr":27.900,"sum_yes":65,"sum_maybe":79,"sum_badimage":197,"avg_agree":0.989,"sum_a_class01":1567,"sum_a_class02":7,"sum_a_class03":18,"sum_a_class04":0,"sum_a_class05":0,"case_no_bad":27,"case_yes_no":21,"case_no_maybe":49,"case_yes_maybe":0,"case_yes_bad":0,"case_maybe_bad":0}
{"project_id":6175,"task_count":344716,"sum_completedcount_corr":1248396,"avg_completedcount_corr":3.622,"sum_yes":4995,"sum_maybe":7148,"sum_badimage":20488,"avg_agree":0.972,"sum_a_class01":327599,"sum_a_class02":3672,"sum_a_class03":5029,"sum_a_class04":8024,"sum_a_class05":392,"case_no_bad":6944,"case_yes_no":3310,"case_no_maybe":6026,"case_yes_maybe":58,"case_yes_bad":92,"case_maybe_bad":210}
{"project_id":6310,"task_count":240020,"sum_completedcount_corr":1762792,"avg_completedcount_corr":7.344,"sum_yes":32528,"sum_maybe":11320,"sum_badimage":9033,"avg_agree":0.953,"sum_a_class01":213359,"sum_a_class02":15921,"sum_a_class03":10065,"sum_a_class04":657,"sum_a_class05":18,"case_no_bad":6095,"case_yes_no":12620,"case_no_maybe":8765,"case_yes_maybe":0,"case_yes_bad":0,"case_maybe_bad":0}
{"project_id":6498,"task_count":91462,"sum_completedcount_corr":365449,"avg_completedcount_corr":4.001,"sum_yes":49068,"sum_maybe":7776,"sum_badimage":12957,"avg_agree":0.874,"sum_a_class01":70783,"sum_a_class02":4332,"sum_a_class03":7927,"sum_a_class04":7588,"sum_a_class05":832,"case_no_bad":5117,"case_yes_no":8320,"case_no_maybe":5059,"case_yes_maybe":381,"case_yes_bad":71,"case_maybe_bad":85}
{"project_id":6628,"task_count":151145,"sum_completedcount_corr":868080,"avg_completedcount_corr":5.746,"sum_yes":67978,"sum_maybe":19487,"sum_badimage":96039,"avg_agree":0.851,"sum_a_class01":102720,"sum_a_class02":26866,"sum_a_class03":16898,"sum_a_class04":4377,"sum_a_class05":284,"case_no_bad":22386,"case_yes_no":8161,"case_no_maybe":11311,"case_yes_maybe":433,"case_yes_bad":388,"case_maybe_bad":611}
{"project_id":6637,"task_count":102012,"sum_completedcount_corr":419324,"avg_completedcount_corr":4.112,"sum_yes":29242,"sum_maybe":5055,"sum_badimage":15058,"avg_agree":0.919,"sum_a_class01":86823,"sum_a_class02":3594,"sum_a_class03":6512,"sum_a_class04":4370,"sum_a_class05":713,"case_no_bad":5736,"case_yes_no":4471,"case_no_maybe":3457,"case_yes_maybe":168,"case_yes_bad":80,"case_maybe_bad":117}
{"project_id":6646,"task_count":46999,"sum_completedcount_corr":255069,"avg_completedcount_corr":5.428,"sum_yes":12889,"sum_maybe":3406,"sum_badimage":19146,"avg_agree":0.894,"sum_a_class01":36022,"sum_a_class02":7114,"sum_a_class03":3124,"sum_a_class04":720,"sum_a_class05":19,"case_no_bad":5637,"case_yes_no":1970,"case_no_maybe":1971,"case_yes_maybe":29,"case_yes_bad":70,"case_maybe_bad":214}
{"project_id":6807,"task_count":304605,"sum_completedcount_corr":1151478,"avg_completedcount_corr":3.781,"sum_yes":52656,"sum_maybe":19889,"sum_badimage":145901,"avg_agree":0.826,"sum_a_class01":213731,"sum_a_class02":10390,"sum_a_class03":35405,"sum_a_class04":41611,"sum_a_class05":3468,"case_no_bad":56817,"case_yes_no":13943,"case_no_maybe":13505,"case_yes_maybe":476,"case_yes_bad":374,"case_maybe_bad":966}
{"project_id":7056,"task_count":112702,"sum_completedcount_corr":423324,"avg_completedcount_corr":3.758,"sum_yes":67676,"sum_maybe":8713,"sum_badimage":11195,"avg_agree":0.881,"sum_a_class01":89879,"sum_a_class02":3245,"sum_a_class03":7915,"sum_a_class04":10311,"sum_a_class05":1352,"case_no_bad":2901,"case_yes_no":11611,"case_no_maybe":5055,"case_yes_maybe":844,"case_yes_bad":145,"case_maybe_bad":235}
{"project_id":7124,"task_count":10379,"sum_completedcount_corr":41749,"avg_completedcount_corr":4.026,"sum_yes":7579,"sum_maybe":650,"sum_badimage":6,"avg_agree":0.902,"sum_a_class01":8554,"sum_a_class02":217,"sum_a_class03":977,"sum_a_class04":502,"sum_a_class05":129,"case_no_bad":3,"case_yes_no":1221,"case_no_maybe":335,"case_yes_maybe":95,"case_yes_bad":3,"case_maybe_bad":0}
